orger/__init__.py
orger/atomic_append.py
orger/common.py
orger/inorganic.py
orger/logging_helper.py
orger/org_view.py
orger/pandoc.py
orger/py.typed
orger/state.py
orger/modules/auto.py
orger/modules/github.py
orger/modules/hyp2org.py
orger/modules/hypothesis.py
orger/modules/instapaper.py
orger/modules/ip2org.py
orger/modules/kobo.py
orger/modules/kobo2org.py
orger/modules/krill.py
orger/modules/materialistic.py
orger/modules/movies.py
orger/modules/pdfs.py
orger/modules/pinboard.py
orger/modules/pocket.py
orger/modules/pocket_demo.py
orger/modules/polar.py
orger/modules/reddit2org.py
orger/modules/reddit_all.py
orger/modules/roamresearch.py
orger/modules/rss.py
orger/modules/rtm2org.py
orger/modules/stackexchange.py
orger/modules/tinder.py
orger/modules/twitter.py
orger/modules/twitter_likes.py
orger/modules/vkfavs.py
orger/modules/youtube.py
orger/modules/zotero.py
orger/modules/zulip.py
orger-0.5.20251008.dist-info/METADATA
orger-0.5.20251008.dist-info/WHEEL
orger-0.5.20251008.dist-info/licenses/LICENSE
orger-0.5.20251008.dist-info/RECORD
