Metadata-Version: 2.4
Name: orger
Version: 0.5.20251008
Summary: Converts data into org-mode
Project-URL: Homepage, https://github.com/karlicoss/orger
Author-email: "Dima Gerasimov (@karlicoss)" <karlicoss@gmail.com>
Maintainer-email: "Dima Gerasimov (@karlicoss)" <karlicoss@gmail.com>
License: MIT License
License-File: LICENSE
Requires-Python: >=3.12
Requires-Dist: atomicwrites
Requires-Dist: platformdirs
Provides-Extra: optional
Requires-Dist: colorlog; extra == 'optional'
